Workbook

Sheet Fragenkatalog
A1: Archivfragen – 1.000 Multiple-Choice-Fragen
A2: Überwiegend deutschsprachiger Raum · 17 Themengebiete · 15 ansteigende Schwierigkeitsstufen
A4: ID | B4: Themengebiet | C4: Stufe | D4: Niveau | E4: Frage | F4: Antwort A | G4: Antwort B | H4: Antwort C | I4: Antwort D | J4: Richtige Option | K4: Richtige Antwort | L4: Kurzbegründung | M4: Quelle
A5: AR-0001 | B5: Archive und Archivtypen | C5: 1 | D5: Einstieg | E5: In welchem Archivtyp erwartet man typischerweise Geschäftsberichte, Werbemittel und historische Produktfotografien eines Konzerns? | F5: Unternehmensarchiv | G5: Universitätsarchiv | H5: Parlamentsarchiv | I5: Pfarrarchiv | J5: A | K5: Unternehmensarchiv | L5: Unternehmensarchive sichern unter anderem Schriftdokumente, Fotos, Filme, Werbemittel und Publikationen aus der Unternehmensentwicklung. | M5: https://www.wirtschaftsarchive.de/ueber-uns/mission/
A6: AR-0002 | B6: Archive und Archivtypen | C6: 1 | D6: Einstieg | E6: Welche Unterlagen sind besonders typisch für ein kirchliches Archiv? | F6: Börsenkurszettel des Wertpapierhandels | G6: Kirchenbücher mit Taufen, Trauungen und Sterbefällen | H6: Flugpläne mit Start- und Landezeiten | I6: Patentschriften zu Maschinenbauteilen | J6: B | K6: Kirchenbücher mit Taufen, Trauungen und Sterbefällen | L6: Kirchenbücher dokumentieren insbesondere Taufen, Trauungen und Sterbefälle und bilden eine zentrale kirchliche Archivquelle. | M6: https://www.ekd.de/archion-ahnenforschung-im-internet-27955.htm
A7: AR-0003 | B7: Archive und Archivtypen | C7: 1 | D7: Einstieg | E7: Welcher Archivtyp ist in erster Linie für die historische Überlieferung einer Stadtverwaltung zuständig? | F7: Bistumsarchiv | G7: Unternehmensarchiv | H7: Stadtarchiv | I7: Rundfunkarchiv | J7: C | K7: Stadtarchiv | L7: Ein Stadtarchiv übernimmt und bewahrt archivwürdige Unterlagen der städtischen Organe und Dienststellen. | M7: https://www.wien.gv.at/bildung/wiener-stadt-landesarchiv-bestand
A8: AR-0004 | B8: Archive und Archivtypen | C8: 1 | D8: Einstieg | E8: Welches Merkmal ist für ein öffentliches Archiv besonders kennzeichnend? | F8: Ein grundsätzlich auf Kunstobjekte beschränkter Bestand | G8: Eine ausschließlich ehrenamtliche Trägerschaft | H8: Ein auf käufliche Druckwerke begrenzter Sammelauftrag | I8: Ein rechtlich festgelegter Zuständigkeitsbereich für Unterlagen öffentlicher Stellen | J8: D | K8: Ein rechtlich festgelegter Zuständigkeitsbereich für Unterlagen öffentlicher Stellen | L8: Öffentliche Archive besitzen regelmäßig einen gesetzlich oder satzungsrechtlich bestimmten Archivsprengel. | M8: https://www.bundesarchiv.de/das-bundesarchiv/aufgaben/
A9: AR-0005 | B9: Archivgeschichte | C9: 1 | D9: Einstieg | E9: In welchem historischen Umbruch entstanden 1790 die französischen Archives nationales? | F9: In der Französischen Revolution. | G9: Im Hundertjährigen Krieg. | H9: Während der Pariser Kommune 1871. | I9: In der Julikrise 1914. | J9: A | K9: In der Französischen Revolution. | L9: Die Nationalarchive wurden durch die revolutionäre Neuordnung des französischen Staates geschaffen. | M9: https://www.archives-nationales.culture.gouv.fr/qui-sommes-nous
A10: AR-0006 | B10: Archivgeschichte | C10: 1 | D10: Einstieg | E10: In welchem Jahr wurde das Bundesarchiv der Bundesrepublik Deutschland gegründet? | F10: 1963. | G10: 1952. | H10: 1945. | I10: 1919. | J10: B | K10: 1952. | L10: Das Bundesarchiv nahm 1952 in Koblenz seine Arbeit auf. | M10: https://www.bundesarchiv.de/das-bundesarchiv/geschichte-des-bundesarchivs/
A11: AR-0007 | B11: Archivgeschichte | C11: 1 | D11: Einstieg | E11: Welche 1919 geschaffene Institution gilt als Vorläufer des deutschen Bundesarchivs? | F11: Das Reichskammergerichtsarchiv. | G11: Das Deutsche Literaturarchiv. | H11: Das Reichsarchiv. | I11: Das Geheime Hausarchiv. | J11: C | K11: Das Reichsarchiv. | L11: Das Reichsarchiv wurde 1919 eingerichtet und ist der institutionelle Vorläufer des Bundesarchivs. | M11: https://www.bundesarchiv.de/das-bundesarchiv/geschichte-des-bundesarchivs/
A12: AR-0008 | B12: Archivgeschichte | C12: 1 | D12: Einstieg | E12: Wer gründete 1749 das Wiener Haus-, Hof- und Staatsarchiv? | F12: Kaiserin Elisabeth. | G12: Kaiser Joseph II. | H12: Erzherzog Franz Ferdinand. | I12: Kaiserin Maria Theresia. | J12: D | K12: Kaiserin Maria Theresia. | L12: Maria Theresia initiierte 1749 die Zusammenführung zentraler habsburgischer Rechts- und Herrschaftstitel. | M12: https://www.oesta.gv.at/ueber-uns/geschichte/haus-hof-und-staatsarchiv2.html
A13: AR-0009 | B13: Archivtechnik | C13: 1 | D13: Einstieg | E13: Warum sind Magazine normalerweise von Lesesaal und Büro getrennt? | F13: Um Klima, Sicherheit, Brandschutz und Zutritt gezielt steuern zu können | G13: Damit Signaturen im Lesesaal ungültig werden | H13: Damit Archivgut ohne Findmittel bleibt | I13: Damit in Magazinen dauerhaft Tageslicht einfällt | J13: A | K13: Um Klima, Sicherheit, Brandschutz und Zutritt gezielt steuern zu können | L13: Funktionsbereiche haben unterschiedliche Nutzungs- und Risikoprofile und werden baulich beziehungsweise organisatorisch getrennt. | M13: https://www.dinmedia.de/en/standard/din-en-16893/276155794
A14: AR-0010 | B14: Archivtechnik | C14: 1 | D14: Einstieg | E14: Welche Aufgabe erfüllt ein Archivmagazin? | F14: Es ersetzt die archivische Bewertung | G14: Es dient der sicheren, geordneten und langfristigen Aufbewahrung von Archivgut | H14: Es ist ausschließlich ein öffentlicher Veranstaltungsraum | I14: Es dient nur der Zwischenlagerung von Büromaterial | J14: B | K14: Es dient der sicheren, geordneten und langfristigen Aufbewahrung von Archivgut | L14: Magazinbau, Ausstattung und Betrieb sind auf Schutz, Ordnung und kontrollierten Zugang ausgerichtet. | M14: https://www.iso.org/standard/82306.html
A15: AR-0011 | B15: Archivtechnik | C15: 1 | D15: Einstieg | E15: Welches Gerät zeichnet Temperatur und relative Luftfeuchte über die Zeit auf? | F15: Ein Buchscanner | G15: Ein Mikrofilmleser | H15: Ein Datenlogger | I15: Ein Aktenvernichter | J15: C | K15: Ein Datenlogger | L15: Zeitreihen zeigen Schwankungen und Ausfälle, die einzelne Momentmessungen nicht erfassen. | M15: https://www.canada.ca/en/conservation-institute/services/agents-deterioration/humidity/video-monitoring-your-environment.html
A16: AR-0012 | B16: Archivtechnik | C16: 1 | D16: Einstieg | E16: Wie werden großformatige Pläne in gutem Zustand bevorzugt gelagert? | F16: Eng gefaltet in Standardbriefumschlägen | G16: Mit Klebeband an der Magazinwand | H16: Lose über Heizkörpern hängend | I16: Flach in ausreichend großen Planschränken oder geeigneten Großformatboxen | J16: D | K16: Flach in ausreichend großen Planschränken oder geeigneten Großformatboxen | L16: Flachlagerung vermeidet neue Falten, Randdruck und unnötige Rollspannung. | M16: https://www.archives.gov/preservation/holdings-maintenance
... A1004: AR-1000 | B1004: Sphragistik | C1004: 15 | D1004: Absurd schwer | E1004: Wie weichen Zacos/Veglery und Laurent bei der Datierung der Agallianos-Siegel voneinander ab? | F1004: 6. Jahrhundert gegenüber 10. Jahrhundert | G1004: 11. Jahrhundert gegenüber 12. Jahrhundert | H1004: Mitte 7. Jahrhundert gegenüber frühes 7. Jahrhundert | I1004: 787-815 gegenüber zweiter Hälfte des 9. Jahrhunderts | J1004: D | K1004: 787-815 gegenüber zweiter Hälfte des 9. Jahrhunderts | L1004: Zacos/Veglery setzen die Stücke zwischen die beiden Ikonoklasmusphasen; Laurent plädiert für die zweite Hälfte des 9. Jahrhunderts. | M1004: https://pbe.kcl.ac.uk/data/D00/F82.htm

Sheet Übersicht
A1: Übersicht des Fragenkatalogs
A3: Kennzahl | B3: Wert
A4: Fragen gesamt | B4: =COUNTA(Fragenkatalog!$A$5:$A$1004) -> 1000
A5: Themengebiete | B5: =COUNTA($A$9:$A$25) -> 17
A8: Themengebiet | B8: Anzahl | D8: Stufe | E8: Niveau | F8: Anzahl
A9: Archive und Archivtypen | B9: =COUNTIF(Fragenkatalog!$B$5:$B$1004,A9) -> 60 | D9: 1 | E9: Einstieg | F9: =COUNTIF(Fragenkatalog!$C$5:$C$1004,D9) -> 70
A10: Archivgeschichte | B10: =COUNTIF(Fragenkatalog!$B$5:$B$1004,A10) -> 57 | D10: 2 | E10: Sehr leicht | F10: =COUNTIF(Fragenkatalog!$C$5:$C$1004,D10) -> 70
A11: Archivtechnik | B11: =COUNTIF(Fragenkatalog!$B$5:$B$1004,A11) -> 62 | D11: 3 | E11: Leicht | F11: =COUNTIF(Fragenkatalog!$C$5:$C$1004,D11) -> 70
A12: Archivtheorie | B12: =COUNTIF(Fragenkatalog!$B$5:$B$1004,A12) -> 57 | D12: 4 | E12: Grundlagen | F12: =COUNTIF(Fragenkatalog!$C$5:$C$1004,D12) -> 70
A13: Archivwesen | B13: =COUNTIF(Fragenkatalog!$B$5:$B$1004,A13) -> 60 | D13: 5 | E13: Solide Grundlagen | F13: =COUNTIF(Fragenkatalog!$C$5:$C$1004,D13) -> 70
A14: Archivwissenschaft | B14: =COUNTIF(Fragenkatalog!$B$5:$B$1004,A14) -> 60 | D14: 6 | E14: Fortgeschrittene Grundlagen | F14: =COUNTIF(Fragenkatalog!$C$5:$C$1004,D14) -> 65
A15: Benutzungsbetreuung | B15: =COUNTIF(Fragenkatalog!$B$5:$B$1004,A15) -> 56 | D15: 7 | E15: Mittelschwer | F15: =COUNTIF(Fragenkatalog!$C$5:$C$1004,D15) -> 65
A16: Bestandserhaltung | B16: =COUNTIF(Fragenkatalog!$B$5:$B$1004,A16) -> 62 | D16: 8 | E16: Anspruchsvoll | F16: =COUNTIF(Fragenkatalog!$C$5:$C$1004,D16) -> 65
A17: Digitale Archivalienkunde | B17: =COUNTIF(Fragenkatalog!$B$5:$B$1004,A17) -> 62 | D17: 9 | E17: Sehr anspruchsvoll | F17: =COUNTIF(Fragenkatalog!$C$5:$C$1004,D17) -> 65
A18: Digitale Langzeitarchivierung | B18: =COUNTIF(Fragenkatalog!$B$5:$B$1004,A18) -> 62 | D18: 10 | E18: Fachniveau | F18: =COUNTIF(Fragenkatalog!$C$5:$C$1004,D18) -> 65
A19: Diplomatik | B19: =COUNTIF(Fragenkatalog!$B$5:$B$1004,A19) -> 56 | D19: 11 | E19: Fortgeschrittenes Fachniveau | F19: =COUNTIF(Fragenkatalog!$C$5:$C$1004,D19) -> 65
A20: Genealogie | B20: =COUNTIF(Fragenkatalog!$B$5:$B$1004,A20) -> 56 | D20: 12 | E20: Expertenniveau | F20: =COUNTIF(Fragenkatalog!$C$5:$C$1004,D20) -> 65
... A23: Paläographie | B23: =COUNTIF(Fragenkatalog!$B$5:$B$1004,A23) -> 57 | D23: 15 | E23: Absurd schwer | F23: =COUNTIF(Fragenkatalog!$C$5:$C$1004,D23) -> 65
A24: Retrodigitalisierung | B24: =COUNTIF(Fragenkatalog!$B$5:$B$1004,A24) -> 62
A25: Sphragistik | B25: =COUNTIF(Fragenkatalog!$B$5:$B$1004,A25) -> 57

Sheet Hinweise
A1: Hinweise zur Nutzung
A3: Punkt | B3: Erläuterung
A4: Ausrichtung | B4: Mehrheitlich Deutschland, Österreich und Schweiz; ergänzt um ausgewählte internationale Standards, Institutionen und Fachbegriffe.
A5: Schwierigkeit | B5: Stufe 1 beginnt mit allgemein verständlichem Grundwissen. Stufe 15 verlangt bewusst seltenes und sehr detailliertes Fachwissen.
A6: Antworten | B6: Die richtige Lösung ist sowohl als Buchstabe in „Richtige Option“ als auch ausgeschrieben in „Richtige Antwort“ angegeben.
A7: Quellen | B7: Die Quellenangaben dienen der fachlichen Nachprüfung. Bei Normen kann der vollständige Text zugangsbeschränkt sein; verlinkt ist dann die offizielle Norm- oder Institutionsseite.
A8: Begriff | B8: Die im Auftrag genannte „Kodiologie“ wird fachsprachlich als „Kodikologie“ geführt.
A9: Sortierung | B9: Der Katalog ist zunächst nach Schwierigkeitsstufe, danach nach Themengebiet und Frage sortiert.
A10: Bearbeitung | B10: Filter und Tabellenformat ermöglichen eine Auswahl nach Themengebiet, Stufe oder richtiger Option.
